circuitpython_kernel/__init__.py
circuitpython_kernel/__main__.py
circuitpython_kernel/board.py
circuitpython_kernel/install.py
circuitpython_kernel/kernel.py
circuitpython_kernel/version.py
circuitpython_kernel-0.2.0.dist-info/DESCRIPTION.rst
circuitpython_kernel-0.2.0.dist-info/METADATA
circuitpython_kernel-0.2.0.dist-info/RECORD
circuitpython_kernel-0.2.0.dist-info/WHEEL
circuitpython_kernel-0.2.0.dist-info/metadata.json
circuitpython_kernel-0.2.0.dist-info/top_level.txt
