Metadata-Version: 2.0
Name: circuitpython-kernel
Version: 0.2.0
Summary: CircuitPython Kernel enables CircuitPython to be used in Jupyter Notebooks for learning Python coding with microcontrollers.
Home-page: https://github.com/willingc/circuitpython_kernel
Author: Carol Willing
Author-email: carolcode@willingconsulting.com
License: BSD license
Keywords: circuitpython_kernel jupyter notebook
Platform: UNKNOWN
Classifier: Development Status :: 2 - Pre-Alpha
Classifier: Intended Audience :: Developers
Classifier: License :: OSI Approved :: BSD License
Classifier: Natural Language :: English
Classifier: Programming Language :: Python :: 3
Classifier: Programming Language :: Python :: 3.4
Classifier: Programming Language :: Python :: 3.5
Classifier: Programming Language :: Python :: 3.6
Requires-Dist: ipykernel
Requires-Dist: ipython
Requires-Dist: pyserial
